autotrello/__init__.py
autotrello/_version.py
autotrello/board_cache.py
autotrello/linked_card.py
autotrello/py.typed
autotrello/recurring_board_cache.py
autotrello/trello_manipulator.py
autotrello-0.2.3.dist-info/LICENSE
autotrello-0.2.3.dist-info/METADATA
autotrello-0.2.3.dist-info/NOTICE
autotrello-0.2.3.dist-info/WHEEL
autotrello-0.2.3.dist-info/top_level.txt
autotrello-0.2.3.dist-info/RECORD
