Metadata-Version: 2.1
Name: autotrello
Version: 0.2.3
Summary: Automation of workflows and high-level access to Trello.
Home-page: https://github.com/mbdevpl/autotrello
Download-URL: 
Author: Mateusz Bysiek
Author-email: mateusz.bysiek@gmail.com
Maintainer: Mateusz Bysiek
Maintainer-email: mateusz.bysiek@gmail.com
License: Apache License 2.0
Keywords: automation,trello
Classifier: Development Status :: 1 - Planning
Classifier: Environment :: Console
Classifier: Intended Audience :: Developers
Classifier: License :: OSI Approved :: Apache Software License
Classifier: Natural Language :: English
Classifier: Operating System :: MacOS
Classifier: Operating System :: Microsoft :: Windows
Classifier: Operating System :: POSIX :: Linux
Classifier: Programming Language :: Python :: 3.11
Classifier: Programming Language :: Python :: 3 :: Only
Classifier: Topic :: Utilities
Requires-Python: >=3.11
License-File: LICENSE
License-File: NOTICE
Requires-Dist: py-trello ~=0.19
Requires-Dist: version-query ~=1.5
